discord_tools/__init__.py
discord_tools/checks.py
discord_tools/converters.py
discord_tools/errors.py
discord_tools/flags.py
discord_tools/models.py
discord_tools/app_commands/__init__.py
discord_tools/app_commands/checks.py
discord_tools/app_commands/context_menu.py
discord_tools/app_commands/enums.py
discord_tools/app_commands/errors.py
discord_tools/app_commands/models.py
discord_tools/app_commands/transformers.py
discord_tools/app_commands/i18n/__init__.py
discord_tools/app_commands/i18n/translator.py
discord_tools/ipc/__init__.py
discord_tools/ipc/_types.py
discord_tools/ipc/response.py
discord_tools/ipc/route.py
discord_tools/ipc/server.py
discord_tools/ipc/session.py
discord_tools/ipc/state.py
discord.py_tools-1.0.0.dist-info/LICENSE
discord.py_tools-1.0.0.dist-info/METADATA
discord.py_tools-1.0.0.dist-info/WHEEL
discord.py_tools-1.0.0.dist-info/top_level.txt
discord.py_tools-1.0.0.dist-info/RECORD
