Metadata-Version: 2.1
Name: discord.py-tools
Version: 1.0.0
Summary: Simple tools for discord.py
Author: Developer Anonymous
License: The MIT License (MIT)
Classifier: Development Status :: 2 - Pre-Alpha
Classifier: License :: OSI Approved :: MIT License
Classifier: Intended Audience :: Developers
Classifier: Natural Language :: English
Classifier: Operating System :: OS Independent
Classifier: Programming Language :: Python :: 3.9
Classifier: Programming Language :: Python :: 3.10
Classifier: Programming Language :: Python :: 3.11
Classifier: Programming Language :: Python :: 3.12
Classifier: Programming Language :: Python :: 3.13
Classifier: Topic :: Internet
Classifier: Topic :: Software Development :: Localization
Requires-Python: >=3.9
License-File: LICENSE
Provides-Extra: po-i18n
Requires-Dist: polib==1.2.0; extra == "po-i18n"
Provides-Extra: yaml-i18n
Requires-Dist: pyyaml<7.0.0; extra == "yaml-i18n"
Provides-Extra: docs
Requires-Dist: sphinx==8.0.2; extra == "docs"
Requires-Dist: sphinxcontrib_trio==1.1.2; extra == "docs"
Requires-Dist: sphinxcontrib-websupport==2.0.0; extra == "docs"
Requires-Dist: myst-parser[linkify]==4.0.0; extra == "docs"
Requires-Dist: sphinxext-opengraph==0.9.1; extra == "docs"
Requires-Dist: sphinx-copybutton==0.5.2; extra == "docs"
Requires-Dist: furo==2024.8.6; extra == "docs"
Requires-Dist: sphinx-autodoc-typehints==2.2.3; extra == "docs"
Requires-Dist: sphinx-intl==2.2.0; extra == "docs"
Requires-Dist: typing_extensions==4.12.2; extra == "docs"
Requires-Dist: levenshtein==0.25.1; extra == "docs"
Requires-Dist: discord.py; extra == "docs"
Provides-Extra: speed
Requires-Dist: orjson>=3.5.4; extra == "speed"
Requires-Dist: aiodns>=1.1; sys_platform != "win32" and extra == "speed"
Requires-Dist: Brotli; extra == "speed"
Requires-Dist: cchardet==2.1.7; python_version < "3.10" and extra == "speed"
Requires-Dist: discord.py[speed]; extra == "speed"
Provides-Extra: voice
Requires-Dist: discord.py[voice]; extra == "voice"
Requires-Dist: libnacl==1.6.0; extra == "voice"
